scheduled_task/__init__.py
scheduled_task/timeconverter.py
scheduled_task/utils.py
scheduled_task-1.0.1.dist-info/LICENSE
scheduled_task-1.0.1.dist-info/METADATA
scheduled_task-1.0.1.dist-info/WHEEL
scheduled_task-1.0.1.dist-info/top_level.txt
scheduled_task-1.0.1.dist-info/RECORD
