Metadata-Version: 2.1
Name: scheduled-task
Version: 1.0.1
Summary: scheduled tasks for Python 3
Home-page: https://github.com/Kryvonis/scheduled_task
Author: Artem Kryvonis
Author-email: me@kryvonis.com
License: MIT
Platform: UNKNOWN
Classifier: Operating System :: OS Independent
Classifier: Intended Audience :: Developers
Classifier: Programming Language :: Python
Classifier: Programming Language :: Python :: 2
Classifier: Programming Language :: Python :: 3
